holdmybeer/__init__.py
holdmybeer/complex.py
holdmybeer/core.py
holdmybeer/exceptions.py
holdmybeer/operations.py
holdmybeer/util.py
holdmybeer-0.0.2.dist-info/DESCRIPTION.rst
holdmybeer-0.0.2.dist-info/METADATA
holdmybeer-0.0.2.dist-info/RECORD
holdmybeer-0.0.2.dist-info/WHEEL
holdmybeer-0.0.2.dist-info/metadata.json
holdmybeer-0.0.2.dist-info/top_level.txt
