Metadata-Version: 2.0
Name: holdmybeer
Version: 0.0.2
Summary: Formalize managing inventory as product buckets.
Home-page: http://tmiedema.com
Author: Thijs Miedema
Author-email: mail@tmiedema.com
License: MIT
Platform: UNKNOWN
